xseed_maxbox/__init__.py
xseed_maxbox/data/docker-compose.yml
xseed_maxbox/sub_modules/__init__.py
xseed_maxbox/sub_modules/buildInstall.py
xseed_maxbox/sub_modules/changeUser.py
xseed_maxbox/sub_modules/config.py
xseed_maxbox/sub_modules/configureMasterBox.py
xseed_maxbox/sub_modules/dockerCompose.py
xseed_maxbox/sub_modules/encryption.py
xseed_maxbox/sub_modules/graphQL.py
xseed_maxbox/sub_modules/installCommonPackagesTools.py
xseed_maxbox/sub_modules/lockAppsOnLauncher.py
xseed_maxbox/sub_modules/packageCleanUp.py
xseed_maxbox/sub_modules/prerequisiteChecks.py
xseed_maxbox-5.7.data/scripts/xseed_maxbox
xseed_maxbox-5.7.dist-info/METADATA
xseed_maxbox-5.7.dist-info/WHEEL
xseed_maxbox-5.7.dist-info/top_level.txt
xseed_maxbox-5.7.dist-info/RECORD
