Metadata-Version: 2.1
Name: xseed-maxbox
Version: 5.7
Summary: Max box setup package
Home-page: UNKNOWN
Author: Mayank Jain
Author-email: Mayank.jain@xseededucation.com
License: UNKNOWN
Platform: UNKNOWN
Classifier: Programming Language :: Python :: 3
Classifier: License :: OSI Approved :: MIT License
Classifier: Operating System :: OS Independent
